Workbook

Sheet Brands
A1: ID | B1: Name Tên hãng | C1: Description Mô tả
A2: 1 | B2: Apple | C2: Apple Inc. designs, manufactures and markets smartphones, personal computers, tablets, wearables and accessories, and sells a variety of related services.
A3: 2 | B3: Samsung | C3: Samsung, South Korean company that is one of the world's largest producers of electronic devices.
A4: 3 | B4: JBL | C4: Always leading speaker trends worldwide, JBL Speakers is a famous speaker brand from the United States, making a strong impression worldwide with its unique design, distinctive sound, and combination of many advanced utilities.
A5: 4 | B5: LG | C5: LG Electronics Inc. is a Korean multinational electronics company.

Sheet Categories
A1: ID | B1: Name Tên loại hàng | C1: Description Mô tả
A2: 1 | B2: Watch | C2: Watch, portable timepiece that has a movement driven either by spring or by electricity and that is designed to be worn or carried in the pocket.
A3: 2 | B3: Phone | C3: A mobile phone (or cellphone[a]) is a portable telephone that can make and receive calls over a radio frequency link while the user is moving within a telephone service area, as opposed to a fixed-location phone (landline phone).
A4: 3 | B4: Laptop | C4: A laptop, sometimes called a notebook computer by manufacturers, is a battery- or AC-powered personal computer (PC) smaller than a briefcase.
A5: 4 | B5: Headphone | C5: An equipments to put on your ear to listen music.

Sheet Products
A1: Code | B1: Name Tên sản phẩm | C1: Amount Số lượng *Từ 1 trở lên | D1: Category Loại sản phẩm | F1: Brand Thương hiệu | H1: Buying Prices Giá mua *Tối thiểu 100$ | J1: Selling Prices Giá bán *Tối thiểu 100$ | L1: Storages Tồn kho *Từ 0 trở lên | M1: Link hình (Trong database) | N1: Mã màu | R1: Đã thêm | S1: Tổng số sản phẩm | T1: =COUNTA(A4:A32,A34:A63,A65:A89,A91:A112) -> 101
D2: Tên | E2: Mã (Trong database) | F2: Tên | G2: Mã (Trong database) | N2: R | O2: G | P2: B | Q2: Mã hex
A3: Tai nghe
A4: SGB2P | B4: Samsung Galaxy Buds 2 Pro | C4: 1 | D4: Headphone | E4: =IF(D4 = "","", INDEX(Categories!$A$2:$A$5, MATCH(D4,Categories!$B$2:$B$5, 0))) -> 4 | F4: Samsung | G4: =IF(F4 = "","",INDEX(Brands!$A$2:$A$5, MATCH(F4,Brands!$B$2:$B$5))) -> 2 | H4: 124 | J4: 207 | L4: 944 | M4: /storage/images/Samsung Galaxy Buds 2 Pro.png | N4: 195 | O4: 183 | P4: 211 | Q4: #C3B7D3 | R4: x
A5: SGB2 | B5: Samsung Galaxy Buds 2 | C5: 1 | D5: Headphone | E5: =IF(D5 = "","", INDEX(Categories!$A$2:$A$5, MATCH(D5,Categories!$B$2:$B$5, 0))) -> 4 | F5: Samsung | G5: =IF(F5 = "","",INDEX(Brands!$A$2:$A$5, MATCH(F5,Brands!$B$2:$B$5))) -> 2 | H5: 100 | J5: 124 | L5: 824 | M5: /storage/images/Samsung Galaxy Buds 2.png | N5: 237 | O5: 237 | P5: 237 | Q5: #EDEDED | R5: x
A6: SGBFE | B6: Samsung Galaxy Buds FE | C6: 1 | D6: Headphone | E6: =IF(D6 = "","", INDEX(Categories!$A$2:$A$5, MATCH(D6,Categories!$B$2:$B$5, 0))) -> 4 | F6: Samsung | G6: =IF(F6 = "","",INDEX(Brands!$A$2:$A$5, MATCH(F6,Brands!$B$2:$B$5))) -> 2 | H6: 100 | J6: 110 | L6: 205 | M6: /storage/images/Samsung Galaxy Buds FE.png | N6: 196 | O6: 184 | P6: 213 | Q6: #C4B8D5 | R6: x
E7: =IF(D7 = "","", INDEX(Categories!$A$2:$A$5, MATCH(D7,Categories!$B$2:$B$5, 0))) | G7: =IF(F7 = "","",INDEX(Brands!$A$2:$A$5, MATCH(F7,Brands!$B$2:$B$5)))
A8: AA3M | B8: Apple AirPods 3 MagSafe | C8: 1 | D8: Headphone | E8: =IF(D8 = "","", INDEX(Categories!$A$2:$A$5, MATCH(D8,Categories!$B$2:$B$5, 0))) -> 4 | F8: Apple | G8: =IF(F8 = "","",INDEX(Brands!$A$2:$A$5, MATCH(F8,Brands!$B$2:$B$5))) -> 1 | H8: 165 | J8: 198 | L8: 161 | M8: /storage/images/Apple AirPods 3 MagSafe.png | N8: 228 | O8: 229 | P8: 233 | Q8: #E4E5E9 | R8: x
A9: AA3 | B9: Apple AirPods 3 | C9: 1 | D9: Headphone | E9: =IF(D9 = "","", INDEX(Categories!$A$2:$A$5, MATCH(D9,Categories!$B$2:$B$5, 0))) -> 4 | F9: Apple | G9: =IF(F9 = "","",INDEX(Brands!$A$2:$A$5, MATCH(F9,Brands!$B$2:$B$5))) -> 1 | H9: 165 | J9: 186 | L9: 645 | M9: /storage/images/Apple AirPods 3.png | N9: 228 | O9: 229 | P9: 233 | Q9: #E4E5E9 | R9: x
A10: AAP2USB | B10: Apple AirPods Pro 2 USB-C | C10: 1 | D10: Headphone | E10: =IF(D10 = "","", INDEX(Categories!$A$2:$A$5, MATCH(D10,Categories!$B$2:$B$5, 0))) -> 4 | F10: Apple | G10: =IF(F10 = "","",INDEX(Brands!$A$2:$A$5, MATCH(F10,Brands!$B$2:$B$5))) -> 1 | H10: 227 | J10: 256 | L10: 54 | M10: /storage/images/Apple AirPods Pro 2 USB-C.png | N10: 229 | O10: 231 | P10: 235 | Q10: #E5E7EB | R10: x
A11: AA2 | B11: Apple AirPods 2 | C11: 1 | D11: Headphone | E11: =IF(D11 = "","", INDEX(Categories!$A$2:$A$5, MATCH(D11,Categories!$B$2:$B$5, 0))) -> 4 | F11: Apple | G11: =IF(F11 = "","",INDEX(Brands!$A$2:$A$5, MATCH(F11,Brands!$B$2:$B$5))) -> 1 | H11: 103 | J11: 165 | L11: 849 | M11: /storage/images/Apple AirPods 2.png | N11: 228 | O11: 229 | P11: 233 | Q11: #E4E5E9 | R11: x
A12: AAPM | B12: Apple AirPods Pro Magsafe | C12: 1 | D12: Headphone | E12: =IF(D12 = "","", INDEX(Categories!$A$2:$A$5, MATCH(D12,Categories!$B$2:$B$5, 0))) -> 4 | F12: Apple | G12: =IF(F12 = "","",INDEX(Brands!$A$2:$A$5, MATCH(F12,Brands!$B$2:$B$5))) -> 1 | H12: 165 | J12: 289 | L12: 353 | M12: /storage/images/Apple AirPods Pro Magsafe.png | N12: 230 | O12: 231 | P12: 235 | Q12: #E6E7EB | R12: x
A13: AAP | B13: Apple AirPods Pro 2022 | C13: 1 | D13: Headphone | E13: =IF(D13 = "","", INDEX(Categories!$A$2:$A$5, MATCH(D13,Categories!$B$2:$B$5, 0))) -> 4 | F13: Apple | G13: =IF(F13 = "","",INDEX(Brands!$A$2:$A$5, MATCH(F13,Brands!$B$2:$B$5))) -> 1 | H13: 207 | J13: 256 | L13: 476 | M13: /storage/images/Apple AirPods Pro 2022.png | N13: 231 | O13: 232 | P13: 236 | Q13: #E7E8EC | R13: x
E14: =IF(D14 = "","", INDEX(Categories!$A$2:$A$5, MATCH(D14,Categories!$B$2:$B$5, 0))) | G14: =IF(F14 = "","",INDEX(Brands!$A$2:$A$5, MATCH(F14,Brands!$B$2:$B$5)))
A15: JTF | B15: JBL Tune Flex | C15: 1 | D15: Headphone | E15: =IF(D15 = "","", INDEX(Categories!$A$2:$A$5, MATCH(D15,Categories!$B$2:$B$5, 0))) -> 4 | F15: JBL | G15: =IF(F15 = "","",INDEX(Brands!$A$2:$A$5, MATCH(F15,Brands!$B$2:$B$5))) -> 1 | H15: 100 | J15: 111 | L15: 97 | M15: /storage/images/JBL Tune Flex.png | N15: 51 | O15: 77 | P15: 104 | Q15: #334D68 | R15: x
A16: JT230TWS | B16: JBL Tune 230 TWS | C16: 1 | D16: Headphone | E16: =IF(D16 = "","", INDEX(Categories!$A$2:$A$5, MATCH(D16,Categories!$B$2:$B$5, 0))) -> 4 | F16: JBL | G16: =IF(F16 = "","",INDEX(Brands!$A$2:$A$5, MATCH(F16,Brands!$B$2:$B$5))) -> 1 | H16: 100 | J16: 102 | L16: 504 | M16: /storage/images/JBL Tune 230 TWS.png | N16: 220 | O16: 218 | P16: 219 | Q16: #DCDADB | R16: x
A17: JTB | B17: JBL Tune Beam | C17: 1 | D17: Headphone | E17: =IF(D17 = "","", INDEX(Categories!$A$2:$A$5, MATCH(D17,Categories!$B$2:$B$5, 0))) -> 4 | F17: JBL | G17: =IF(F17 = "","",INDEX(Brands!$A$2:$A$5, MATCH(F17,Brands!$B$2:$B$5))) -> 1 | H17: 100 | J17: 102 | L17: 838 | M17: /storage/images/JBL Tune Beam.png | N17: 153 | O17: 149 | P17: 190 | Q17: #9995BE | R17: x
A18: JWB | B18: JBL Wave Beam | C18: 1 | D18: Headphone | E18: =IF(D18 = "","", INDEX(Categories!$A$2:$A$5, MATCH(D18,Categories!$B$2:$B$5, 0))) -> 4 | F18: JBL | G18: =IF(F18 = "","",INDEX(Brands!$A$2:$A$5, MATCH(F18,Brands!$B$2:$B$5))) -> 1 | H18: 100 | I18: 60 | J18: 101 | K18: 62 | L18: 382 | M18: /storage/images/JBL Wave Beam.png | N18: 204 | O18: 175 | P18: 145 | Q18: #CCAF91 | R18: x
A19: JT120TWS | B19: JBL Tune 120 TWS | C19: 1 | D19: Headphone | E19: =IF(D19 = "","", INDEX(Categories!$A$2:$A$5, MATCH(D19,Categories!$B$2:$B$5, 0))) -> 4 | F19: JBL | G19: =IF(F19 = "","",INDEX(Brands!$A$2:$A$5, MATCH(F19,Brands!$B$2:$B$5))) -> 1 | H19: 100 | I19: 83 | J19: 101 | K19: 98 | L19: 321 | M19: /storage/images/JBL Tune 120 TWS.png | N19: 36 | O19: 36 | P19: 34 | Q19: #242222 | R19: x
A20: JT115TWS | B20: JBL Tune 115 TWS | C20: 1 | D20: Headphone | E20: =IF(D20 = "","", INDEX(Categories!$A$2:$A$5, MATCH(D20,Categories!$B$2:$B$5, 0))) -> 4 | F20: JBL | G20: =IF(F20 = "","",INDEX(Brands!$A$2:$A$5, MATCH(F20,Brands!$B$2:$B$5))) -> 1 | H20: 100 | I20: 20 | J20: 101 | K20: 61 | L20: 554 | M20: /storage/images/JBL Tune 115 TWS.png | N20: 61 | O20: 61 | P20: 63 | Q20: #3D3D3F | R20: x
A21: JLP2 | B21: JBL Live Pro 2 | C21: 1 | D21: Headphone | E21: =IF(D21 = "","", INDEX(Categories!$A$2:$A$5, MATCH(D21,Categories!$B$2:$B$5, 0))) -> 4 | F21: JBL | G21: =IF(F21 = "","",INDEX(Brands!$A$2:$A$5, MATCH(F21,Brands!$B$2:$B$5))) -> 1 | H21: 103 | J21: 165 | L21: 840 | M21: /storage/images/JBL Live Pro 2.png | N21: 108 | O21: 122 | P21: 161 | Q21: #6C7AA1 | R21: x
A22: JTP2 | B22: JBL Tour Pro 2 | C22: 1 | D22: Headphone | E22: =IF(D22 = "","", INDEX(Categories!$A$2:$A$5, MATCH(D22,Categories!$B$2:$B$5, 0))) -> 4 | F22: JBL | G22: =IF(F22 = "","",INDEX(Brands!$A$2:$A$5, MATCH(F22,Brands!$B$2:$B$5))) -> 1 | H22: 185 | J22: 247 | L22: 818 | M22: /storage/images/JBL Tour Pro 2.png | N22: 46 | O22: 46 | P22: 46 | Q22: #2E2E2E | R22: x
A23: JLP | B23: JBL Live Pro+ | C23: 1 | D23: Headphone | E23: =IF(D23 = "","", INDEX(Categories!$A$2:$A$5, MATCH(D23,Categories!$B$2:$B$5, 0))) -> 4 | F23: JBL | G23: =IF(F23 = "","",INDEX(Brands!$A$2:$A$5, MATCH(F23,Brands!$B$2:$B$5))) -> 1 | H23: 100 | I23: 83 | J23: 124 | L23: 29 | M23: /storage/images/JBL Live Pro+.png | N23: 220 | O23: 186 | P23: 187 | Q23: #DCBABB | R23: x
A24: JCP | B24: JBL Club Pro+ | C24: 1 | D24: Headphone | E24: =IF(D24 = "","", INDEX(Categories!$A$2:$A$5, MATCH(D24,Categories!$B$2:$B$5, 0))) -> 4 | F24: JBL | G24: =IF(F24 = "","",INDEX(Brands!$A$2:$A$5, MATCH(F24,Brands!$B$2:$B$5))) -> 1 | H24: 144 | J24: 206 | L24: 16 | M24: /storage/images/JBL Club Pro+.png | N24: 36 | O24: 36 | P24: 36 | Q24: #242424 | R24: x
A25: JT770NC | B25: JBL Tune 770NC | C25: 1 | D25: Headphone | E25: =IF(D25 = "","", INDEX(Categories!$A$2:$A$5, MATCH(D25,Categories!$B$2:$B$5, 0))) -> 4 | F25: JBL | G25: =IF(F25 = "","",INDEX(Brands!$A$2:$A$5, MATCH(F25,Brands!$B$2:$B$5))) -> 1 | H25: 124 | J25: 144 | L25: 722 | M25: /storage/images/JBL Tune 770NC.png | N25: 73 | O25: 84 | P25: 109 | Q25: #49546D | R25: x
A26: JT670NC | B26: JBL Tune 670NC | C26: 1 | D26: Headphone | E26: =IF(D26 = "","", INDEX(Categories!$A$2:$A$5, MATCH(D26,Categories!$B$2:$B$5, 0))) -> 4 | F26: JBL | G26: =IF(F26 = "","",INDEX(Brands!$A$2:$A$5, MATCH(F26,Brands!$B$2:$B$5))) -> 1 | H26: 100 | J26: 102 | L26: 782 | M26: /storage/images/JBL Tune 670NC.png | N26: 154 | O26: 146 | P26: 187 | Q26: #9A92BB | R26: x
A27: JL670NC | B27: JBL Live 670NC | C27: 1 | D27: Headphone | E27: =IF(D27 = "","", INDEX(Categories!$A$2:$A$5, MATCH(D27,Categories!$B$2:$B$5, 0))) -> 4 | F27: JBL | G27: =IF(F27 = "","",INDEX(Brands!$A$2:$A$5, MATCH(F27,Brands!$B$2:$B$5))) -> 1 | H27: 103 | J27: 124 | L27: 51 | M27: /storage/images/JBL Live 670NC.png | N27: 32 | O27: 32 | P27: 32 | Q27: #202020 | R27: x
A28: JT520BT | B28: JBL Tune 520BT | C28: 1 | D28: Headphone | E28: =IF(D28 = "","", INDEX(Categories!$A$2:$A$5, MATCH(D28,Categories!$B$2:$B$5, 0))) -> 4 | F28: JBL | G28: =IF(F28 = "","",INDEX(Brands!$A$2:$A$5, MATCH(F28,Brands!$B$2:$B$5))) -> 1 | H28: 100 | I28: 50 | J28: 101 | K28: 58 | L28: 737 | M28: /storage/images/JBL Tune 520BT.png | N28: 232 | O28: 232 | P28: 232 | Q28: #E8E8E8 | R28: x
A29: JT510BT | B29: JBL Tune 510BT | C29: 1 | D29: Headphone | E29: =IF(D29 = "","", INDEX(Categories!$A$2:$A$5, MATCH(D29,Categories!$B$2:$B$5, 0))) -> 4 | F29: JBL | G29: =IF(F29 = "","",INDEX(Brands!$A$2:$A$5, MATCH(F29,Brands!$B$2:$B$5))) -> 1 | H29: 100 | I29: 41 | J29: 101 | K29: 58 | L29: 633 | M29: /storage/images/JBL Tune 510BT.png | N29: 203 | O29: 190 | P29: 197 | Q29: #CBBEC5 | R29: x
A30: JT500 | B30: JBL Tune 500 | C30: 1 | D30: Headphone | E30: =IF(D30 = "","", INDEX(Categories!$A$2:$A$5, MATCH(D30,Categories!$B$2:$B$5, 0))) -> 4 | F30: JBL | G30: =IF(F30 = "","",INDEX(Brands!$A$2:$A$5, MATCH(F30,Brands!$B$2:$B$5))) -> 1 | H30: 100 | I30: 20 | J30: 101 | K30: 37 | L30: 932 | M30: /storage/images/JBL Tune 500.png | N30: 51 | O30: 51 | P30: 51 | Q30: #333333 | R30: x
A31: JQO | B31: JBL Quantum One | C31: 1 | D31: Headphone | E31: =IF(D31 = "","", INDEX(Categories!$A$2:$A$5, MATCH(D31,Categories!$B$2:$B$5, 0))) -> 4 | F31: JBL | G31: =IF(F31 = "","",INDEX(Brands!$A$2:$A$5, MATCH(F31,Brands!$B$2:$B$5))) -> 1 | H31: 100 | I31: 82 | J31: 226 | L31: 144 | M31: /storage/images/JBL Quantum One.png | N31: 105 | O31: 105 | P31: 105 | Q31: #696969 | R31: x
A32: JQ400 | B32: JBL Quantum 400 | C32: 1 | D32: Headphone | E32: =IF(D32 = "","", INDEX(Categories!$A$2:$A$5, MATCH(D32,Categories!$B$2:$B$5, 0))) -> 4 | F32: JBL | G32: =IF(F32 = "","",INDEX(Brands!$A$2:$A$5, MATCH(F32,Brands!$B$2:$B$5))) -> 1 | H32: 100 | J32: 102 | L32: 657 | M32: /storage/images/JBL Quantum 400.png | N32: 77 | O32: 78 | P32: 80 | Q32: #4D4E50 | R32: x
A33: Điện thoại
A34: IP15PM | B34: iPhone 15 Pro Max | C34: 1 | D34: Phone | E34: =IF(D34 = "","", INDEX(Categories!$A$2:$A$5, MATCH(D34,Categories!$B$2:$B$5, 0))) -> 2 | F34: Apple | G34: =IF(F34 = "","",INDEX(Brands!$A$2:$A$5, MATCH(F34,Brands!$B$2:$B$5))) -> 1 | H34: 2200 | J34: 2500 | L34: 512 | M34: /storage/images/iPhone 15 Pro Max.png | N34: 150 | O34: 146 | P34: 141 | Q34: #96928D | R34: x
A35: IP15P | B35: iPhone 15 Pro | C35: 1 | D35: Phone | E35: =IF(D35 = "","", INDEX(Categories!$A$2:$A$5, MATCH(D35,Categories!$B$2:$B$5, 0))) -> 2 | F35: Apple | G35: =IF(F35 = "","",INDEX(Brands!$A$2:$A$5, MATCH(F35,Brands!$B$2:$B$5))) -> 1 | H35: 1072 | J35: 1196 | L35: 264 | M35: /storage/images/iPhone 15 Pro.png | N35: 72 | O35: 77 | P35: 82 | Q35: #484D52 | R35: x
A36: IP15PL | B36: iPhone 15 Plus | C36: 1 | D36: Phone | E36: =IF(D36 = "","", INDEX(Categories!$A$2:$A$5, MATCH(D36,Categories!$B$2:$B$5, 0))) -> 2 | F36: Apple | G36: =IF(F36 = "","",INDEX(Brands!$A$2:$A$5, MATCH(F36,Brands!$B$2:$B$5))) -> 1 | H36: 948 | J36: 1072 | L36: 713 | M36: /storage/images/iPhone 15 Plus.png | N36: 254 | O36: 228 | P36: 227 | Q36: #FEE4E3 | R36: x
A37: IP15 | B37: iPhone 15 | C37: 1 | D37: Phone | E37: =IF(D37 = "","", INDEX(Categories!$A$2:$A$5, MATCH(D37,Categories!$B$2:$B$5, 0))) -> 2 | F37: Apple | G37: =IF(F37 = "","",INDEX(Brands!$A$2:$A$5, MATCH(F37,Brands!$B$2:$B$5))) -> 1 | H37: 825 | J37: 948 | L37: 942 | M37: /storage/images/iPhone 15.png | N37: 254 | O37: 249 | P37: 227 | Q37: #FEF9E3 | R37: x
A38: IP14PM | B38: iPhone 14 Pro Max | C38: 1 | D38: Phone | E38: =IF(D38 = "","", INDEX(Categories!$A$2:$A$5, MATCH(D38,Categories!$B$2:$B$5, 0))) -> 2 | F38: Apple | G38: =IF(F38 = "","",INDEX(Brands!$A$2:$A$5, MATCH(F38,Brands!$B$2:$B$5))) -> 1 | H38: 1031 | J38: 1237 | L38: 791 | M38: /storage/images/iPhone 14 Pro Max.png | N38: 65 | O38: 59 | P38: 71 | Q38: #413B47 | R38: x
A39: IP14P | B39: iPhone 14 Pro | C39: 1 | D39: Phone | E39: =IF(D39 = "","", INDEX(Categories!$A$2:$A$5, MATCH(D39,Categories!$B$2:$B$5, 0))) -> 2 | F39: Apple | G39: =IF(F39 = "","",INDEX(Brands!$A$2:$A$5, MATCH(F39,Brands!$B$2:$B$5))) -> 1 | H39: 947 | J39: 1155 | L39: 35 | M39: /storage/images/iPhone 14 Pro.png | N39: 65 | O39: 59 | P39: 71 | Q39: #413B47 | R39: x
A40: IP14PL | B40: iPhone 14 Plus | C40: 1 | D40: Phone | E40: =IF(D40 = "","", INDEX(Categories!$A$2:$A$5, MATCH(D40,Categories!$B$2:$B$5, 0))) -> 2 | F40: Apple | G40: =IF(F40 = "","",INDEX(Brands!$A$2:$A$5, MATCH(F40,Brands!$B$2:$B$5))) -> 1 | H40: 784 | J40: 1031 | L40: 787 | M40: /storage/images/iPhone 14 Plus.png | N40: 157 | O40: 174 | P40: 192 | Q40: #9DAEC0 | R40: x
A41: IP14 | B41: iPhone 14 | C41: 1 | D41: Phone | E41: =IF(D41 = "","", INDEX(Categories!$A$2:$A$5, MATCH(D41,Categories!$B$2:$B$5, 0))) -> 2 | F41: Apple | G41: =IF(F41 = "","",INDEX(Brands!$A$2:$A$5, MATCH(F41,Brands!$B$2:$B$5))) -> 1 | H41: 660 | J41: 948 | L41: 729 | M41: /storage/images/iPhone 14.png | N41: 157 | O41: 176 | P41: 193 | Q41: #9DB0C1 | R41: x
A42: IP13PM | B42: iPhone 13 Pro Max | C42: 1 | D42: Phone | E42: =IF(D42 = "","", INDEX(Categories!$A$2:$A$5, MATCH(D42,Categories!$B$2:$B$5, 0))) -> 2 | F42: Apple | G42: =IF(F42 = "","",INDEX(Brands!$A$2:$A$5, MATCH(F42,Brands!$B$2:$B$5))) -> 1 | H42: 866 | J42: 1196 | L42: 755 | M42: /storage/images/iPhone 13 Pro Max.png | N42: 238 | O42: 222 | P42: 198 | Q42: #EEDEC6 | R42: x
A43: IP13P | B43: iPhone 13 Pro | C43: 1 | D43: Phone | E43: =IF(D43 = "","", INDEX(Categories!$A$2:$A$5, MATCH(D43,Categories!$B$2:$B$5, 0))) -> 2 | F43: Apple | G43: =IF(F43 = "","",INDEX(Brands!$A$2:$A$5, MATCH(F43,Brands!$B$2:$B$5))) -> 1 | H43: 990 | J43: 1113 | L43: 496 | M43: /storage/images/iPhone 13 Pro.png | N43: 147 | O43: 163 | P43: 188 | Q43: #93A3BC | R43: x
A44: IP13 | B44: iPhone 13 | C44: 1 | D44: Phone | E44: =IF(D44 = "","", INDEX(Categories!$A$2:$A$5, MATCH(D44,Categories!$B$2:$B$5, 0))) -> 2 | F44: Apple | G44: =IF(F44 = "","",INDEX(Brands!$A$2:$A$5, MATCH(F44,Brands!$B$2:$B$5))) -> 1 | H44: 578 | J44: 784 | L44: 719 | M44: /storage/images/iPhone 13.png | N44: 249 | O44: 222 | P44: 215 | Q44: #F9DED7 | R44: x
A45: IP12PM | B45: iPhone 12 Pro Max | C45: 1 | D45: Phone | E45: =IF(D45 = "","", INDEX(Categories!$A$2:$A$5, MATCH(D45,Categories!$B$2:$B$5, 0))) -> 2 | F45: Apple | G45: =IF(F45 = "","",INDEX(Brands!$A$2:$A$5, MATCH(F45,Brands!$B$2:$B$5))) -> 1 | H45: 947 | J45: 1196 | L45: 761 | M45: /storage/images/iPhone 12 Pro Max.png | N45: 251 | O45: 235 | P45: 210 | Q45: #FBEBD2 | R45: x
... A48: IP11 | B48: iPhone 11 | C48: 1 | D48: Phone | E48: =IF(D48 = "","", INDEX(Categories!$A$2:$A$5, MATCH(D48,Categories!$B$2:$B$5, 0))) -> 2 | F48: Apple | G48: =IF(F48 = "","",INDEX(Brands!$A$2:$A$5, MATCH(F48,Brands!$B$2:$B$5))) -> 1 | H48: 454 | J48: 577 | L48: 0 | M48: /storage/images/iPhone 11.png | N48: 182 | O48: 8 | P48: 45 | Q48: #B6082D | R48: x
E49: =IF(D49 = "","", INDEX(Categories!$A$2:$A$5, MATCH(D49,Categories!$B$2:$B$5, 0))) | G49: =IF(F49 = "","",INDEX(Brands!$A$2:$A$5, MATCH(F49,Brands!$B$2:$B$5)))
A50: SGZF5 | B50: Samsung Galaxy Z Flip 5 | C50: 1 | D50: Phone | E50: =IF(D50 = "","", INDEX(Categories!$A$2:$A$5, MATCH(D50,Categories!$B$2:$B$5, 0))) -> 2 | F50: SamSung | G50: =IF(F50 = "","",INDEX(Brands!$A$2:$A$5, MATCH(F50,Brands!$B$2:$B$5))) -> 2 | H50: 742 | J50: 1237 | L50: 910 | M50: /storage/images/Samsung Galaxy Z Flip 5.png | N50: 224 | O50: 236 | P50: 232 | Q50: #E0ECE8 | R50: x
A51: SGZFL5 | B51: Samsung Galaxy Z Fold 5 | C51: 1 | D51: Phone | E51: =IF(D51 = "","", INDEX(Categories!$A$2:$A$5, MATCH(D51,Categories!$B$2:$B$5, 0))) -> 2 | F51: SamSung | G51: =IF(F51 = "","",INDEX(Brands!$A$2:$A$5, MATCH(F51,Brands!$B$2:$B$5))) -> 2 | H51: 1278 | J51: 1689 | L51: 451 | M51: /storage/images/Samsung Galaxy Z Fold 5.png | N51: 153 | O51: 160 | P51: 179 | Q51: #99A0B3 | R51: x
A52: SS23U5G | B52: Samsung Galaxy S23 Ultra 5G | C52: 1 | D52: Phone | E52: =IF(D52 = "","", INDEX(Categories!$A$2:$A$5, MATCH(D52,Categories!$B$2:$B$5, 0))) -> 2 | F52: SamSung | G52: =IF(F52 = "","",INDEX(Brands!$A$2:$A$5, MATCH(F52,Brands!$B$2:$B$5))) -> 2 | H52: 907 | J52: 1280 | L52: 200 | M52: /storage/images/Samsung Galaxy S23 Ultra 5G.png | N52: 220 | O52: 209 | P52: 219 | Q52: #DCD1DB | R52: x
A53: SS23U | B53: Samsung Galaxy S23 Ultra | C53: 1 | D53: Phone | E53: =IF(D53 = "","", INDEX(Categories!$A$2:$A$5, MATCH(D53,Categories!$B$2:$B$5, 0))) -> 2 | F53: SamSung | G53: =IF(F53 = "","",INDEX(Brands!$A$2:$A$5, MATCH(F53,Brands!$B$2:$B$5))) -> 2 | H53: 1800 | J53: 2000 | L53: 256 | M53: /storage/images/Samsung Galaxy S23 Ultra.png | N53: 78 | O53: 84 | P53: 78 | Q53: #4E544E | R53: x
A54: SS23P | B54: Samsung Galaxy S23 Plus | C54: 1 | D54: Phone | E54: =IF(D54 = "","", INDEX(Categories!$A$2:$A$5, MATCH(D54,Categories!$B$2:$B$5, 0))) -> 2 | F54: SamSung | G54: =IF(F54 = "","",INDEX(Brands!$A$2:$A$5, MATCH(F54,Brands!$B$2:$B$5))) -> 2 | H54: 701 | J54: 1113 | L54: 659 | M54: /storage/images/Samsung Galaxy S23 Plus.png | N54: 244 | O54: 235 | P54: 226 | Q54: #F4EBE2 | R54: x
A55: SS23 | B55: Samsung Galaxy S23 | C55: 1 | D55: Phone | E55: =IF(D55 = "","", INDEX(Categories!$A$2:$A$5, MATCH(D55,Categories!$B$2:$B$5, 0))) -> 2 | F55: SamSung | G55: =IF(F55 = "","",INDEX(Brands!$A$2:$A$5, MATCH(F55,Brands!$B$2:$B$5))) -> 2 | H55: 536 | J55: 948 | L55: 542 | M55: /storage/images/Samsung Galaxy S23.png | N55: 69 | O55: 75 | P55: 65 | Q55: #454B41 | R55: x
A56: SS23FE5G | B56: Samsung Galaxy S23 FE 5G | C56: 1 | D56: Phone | E56: =IF(D56 = "","", INDEX(Categories!$A$2:$A$5, MATCH(D56,Categories!$B$2:$B$5, 0))) -> 2 | F56: SamSung | G56: =IF(F56 = "","",INDEX(Brands!$A$2:$A$5, MATCH(F56,Brands!$B$2:$B$5))) -> 2 | H56: 578 | J56: 619 | L56: 456 | M56: /storage/images/Samsung Galaxy S23 FE 5G.png | N56: 97 | O56: 82 | P56: 113 | Q56: #615271 | R56: x
A57: SS22U | B57: Samsung Galaxy S22 Ultra | C57: 1 | D57: Phone | E57: =IF(D57 = "","", INDEX(Categories!$A$2:$A$5, MATCH(D57,Categories!$B$2:$B$5, 0))) -> 2 | F57: SamSung | G57: =IF(F57 = "","",INDEX(Brands!$A$2:$A$5, MATCH(F57,Brands!$B$2:$B$5))) -> 2 | H57: 681 | J57: 1402 | L57: 867 | M57: /storage/images/Samsung Galaxy S22 Ultra.png | N57: 28 | O57: 28 | P57: 28 | Q57: #1C1C1C | R57: x
A58: SS22P | B58: Samsung Galaxy S22 Plus | C58: 1 | D58: Phone | E58: =IF(D58 = "","", INDEX(Categories!$A$2:$A$5, MATCH(D58,Categories!$B$2:$B$5, 0))) -> 2 | F58: SamSung | G58: =IF(F58 = "","",INDEX(Brands!$A$2:$A$5, MATCH(F58,Brands!$B$2:$B$5))) -> 2 | H58: 660 | J58: 1134 | L58: 606 | M58: /storage/images/Samsung Galaxy S22 Plus.png | N58: 230 | O58: 213 | P58: 205 | Q58: #E6D5CD | R58: x
A59: SS22 | B59: Samsung Galaxy S22 | C59: 1 | D59: Phone | E59: =IF(D59 = "","", INDEX(Categories!$A$2:$A$5, MATCH(D59,Categories!$B$2:$B$5, 0))) -> 2 | F59: SamSung | G59: =IF(F59 = "","",INDEX(Brands!$A$2:$A$5, MATCH(F59,Brands!$B$2:$B$5))) -> 2 | H59: 578 | J59: 969 | L59: 598 | M59: /storage/images/Samsung Galaxy S22.png | N59: 246 | O59: 246 | P59: 246 | Q59: #F6F6F6 | R59: x
A60: SS21U5G | B60: Samsung Galaxy S21 Ultra 5G | C60: 1 | D60: Phone | E60: =IF(D60 = "","", INDEX(Categories!$A$2:$A$5, MATCH(D60,Categories!$B$2:$B$5, 0))) -> 2 | F60: SamSung | G60: =IF(F60 = "","",INDEX(Brands!$A$2:$A$5, MATCH(F60,Brands!$B$2:$B$5))) -> 2 | H60: 1237 | J60: 1278 | L60: 274 | M60: /storage/images/Samsung Galaxy S21 Ultra 5G.png | N60: 24 | O60: 24 | P60: 24 | Q60: #181818 | R60: x
A61: SS21P5G | B61: Samsung Galaxy S21 Plus 5G | C61: 1 | D61: Phone | E61: =IF(D61 = "","", INDEX(Categories!$A$2:$A$5, MATCH(D61,Categories!$B$2:$B$5, 0))) -> 2 | F61: SamSung | G61: =IF(F61 = "","",INDEX(Brands!$A$2:$A$5, MATCH(F61,Brands!$B$2:$B$5))) -> 2 | H61: 1031 | J61: 1072 | L61: 985 | M61: /storage/images/Samsung Galaxy S21 Plus 5G.png | N61: 186 | O61: 202 | P61: 216 | Q61: #BACAD8 | R61: x
... A63: SS21FE5G | B63: Samsung Galaxy S21 FE 5G | C63: 1 | D63: Phone | E63: =IF(D63 = "","", INDEX(Categories!$A$2:$A$5, MATCH(D63,Categories!$B$2:$B$5, 0))) -> 2 | F63: SamSung | G63: =IF(F63 = "","",INDEX(Brands!$A$2:$A$5, MATCH(F63,Brands!$B$2:$B$5))) -> 2 | H63: 456 | J63: 474 | L63: 0 | M63: /storage/images/Samsung Galaxy S21 FE 5G.png | N63: 164 | O63: 166 | P63: 138 | Q63: #A4A68A | R63: x
A64: Laptop
A65: MBP16M3M | B65: Apple Macbook Pro 16 inch M3 Max | C65: 1 | D65: Laptop | E65: =IF(D65 = "","", INDEX(Categories!$A$2:$A$5, MATCH(D65,Categories!$B$2:$B$5, 0))) -> 3 | F65: Apple | G65: =IF(F65 = "","",INDEX(Brands!$A$2:$A$5, MATCH(F65,Brands!$B$2:$B$5))) -> 1 | H65: 3627 | J65: 3710 | L65: 225 | M65: /storage/images/Apple Macbook Pro 16 inch M3 Max.png | N65: 38 | O65: 37 | P65: 40 | Q65: #262528 | R65: x
A66: MBP16M3 | B66: Apple Macbook Pro 16 inch M3 | C66: 1 | D66: Laptop | E66: =IF(D66 = "","", INDEX(Categories!$A$2:$A$5, MATCH(D66,Categories!$B$2:$B$5, 0))) -> 3 | F66: Apple | G66: =IF(F66 = "","",INDEX(Brands!$A$2:$A$5, MATCH(F66,Brands!$B$2:$B$5))) -> 1 | H66: 2556 | J66: 2679 | L66: 631 | M66: /storage/images/Apple Macbook Pro 16 inch M3.png | N66: 208 | O66: 208 | P66: 208 | Q66: #D0D0D0 | R66: x
A67: MBP14M3M | B67: Apple Macbook Pro 14 inch M3 Max | C67: 1 | D67: Laptop | E67: =IF(D67 = "","", INDEX(Categories!$A$2:$A$5, MATCH(D67,Categories!$B$2:$B$5, 0))) -> 3 | F67: Apple | G67: =IF(F67 = "","",INDEX(Brands!$A$2:$A$5, MATCH(F67,Brands!$B$2:$B$5))) -> 1 | H67: 3174 | J67: 3298 | L67: 812 | M67: /storage/images/Apple Macbook Pro 14 inch M3 Max.png | N67: 198 | O67: 198 | P67: 198 | Q67: #C6C6C6 | R67: x
A68: MBP14M3 | B68: Apple Macbook Pro 14 inch M3 | C68: 1 | D68: Laptop | E68: =IF(D68 = "","", INDEX(Categories!$A$2:$A$5, MATCH(D68,Categories!$B$2:$B$5, 0))) -> 3 | F68: Apple | G68: =IF(F68 = "","",INDEX(Brands!$A$2:$A$5, MATCH(F68,Brands!$B$2:$B$5))) -> 1 | H68: 1525 | J68: 1649 | L68: 419 | M68: /storage/images/Apple Macbook Pro 14 inch M3.png | N68: 185 | O68: 185 | P68: 185 | Q68: #B9B9B9 | R68: x
A69: MBP16M2 | B69: Apple MacBook Pro 16 inch M2 | C69: 1 | D69: Laptop | E69: =IF(D69 = "","", INDEX(Categories!$A$2:$A$5, MATCH(D69,Categories!$B$2:$B$5, 0))) -> 3 | F69: Apple | G69: =IF(F69 = "","",INDEX(Brands!$A$2:$A$5, MATCH(F69,Brands!$B$2:$B$5))) -> 1 | H69: 2391 | J69: 2721 | L69: 25 | M69: /storage/images/Apple MacBook Pro 16 inch M2.png | N69: 173 | O69: 175 | P69: 179 | Q69: #ADAFB3 | R69: x
A70: MBP13M2 | B70: Apple Macbook Pro 13 inch M2 | C70: 1 | D70: Laptop | E70: =IF(D70 = "","", INDEX(Categories!$A$2:$A$5, MATCH(D70,Categories!$B$2:$B$5, 0))) -> 3 | F70: Apple | G70: =IF(F70 = "","",INDEX(Brands!$A$2:$A$5, MATCH(F70,Brands!$B$2:$B$5))) -> 1 | H70: 1113 | J70: 1484 | L70: 125 | M70: /storage/images/Apple Macbook Pro 13 inch M2.png | N70: 231 | O70: 231 | P70: 231 | Q70: #E7E7E7 | R70: x
A71: MBAM2 | B71: Apple MacBook Air M2 | C71: 1 | D71: Laptop | E71: =IF(D71 = "","", INDEX(Categories!$A$2:$A$5, MATCH(D71,Categories!$B$2:$B$5, 0))) -> 3 | F71: Apple | G71: =IF(F71 = "","",INDEX(Brands!$A$2:$A$5, MATCH(F71,Brands!$B$2:$B$5))) -> 1 | H71: 1010 | J71: 1320 | L71: 256 | M71: /storage/images/Apple MacBook Air M2.png | N71: 123 | O71: 129 | P71: 135 | Q71: #7B8187 | R71: x
A72: MBP16M1M | B72: Apple Macbook Pro 16 inch M1 Max | C72: 1 | D72: Laptop | E72: =IF(D72 = "","", INDEX(Categories!$A$2:$A$5, MATCH(D72,Categories!$B$2:$B$5, 0))) -> 3 | F72: Apple | G72: =IF(F72 = "","",INDEX(Brands!$A$2:$A$5, MATCH(F72,Brands!$B$2:$B$5))) -> 1 | H72: 2762 | J72: 3833 | L72: 510 | M72: /storage/images/Apple Macbook Pro 16 inch M1 Max.png | N72: 176 | O72: 178 | P72: 179 | Q72: #B0B2B3 | R72: x
A73: MBP14M1 | B73: Apple Macbook Pro 14 inch M1 | C73: 1 | D73: Laptop | E73: =IF(D73 = "","", INDEX(Categories!$A$2:$A$5, MATCH(D73,Categories!$B$2:$B$5, 0))) -> 3 | F73: Apple | G73: =IF(F73 = "","",INDEX(Brands!$A$2:$A$5, MATCH(F73,Brands!$B$2:$B$5))) -> 1 | H73: 1732 | J73: 2721 | L73: 464 | M73: /storage/images/Apple Macbook Pro 14 inch M1.png | N73: 124 | O73: 124 | P73: 126 | Q73: #7C7C7E | R73: x
A74: MBP13TM1 | B74: Apple MacBook Pro 13 inch Touch Bar M1 | C74: 1 | D74: Laptop | E74: =IF(D74 = "","", INDEX(Categories!$A$2:$A$5, MATCH(D74,Categories!$B$2:$B$5, 0))) -> 3 | F74: Apple | G74: =IF(F74 = "","",INDEX(Brands!$A$2:$A$5, MATCH(F74,Brands!$B$2:$B$5))) -> 1 | H74: 1113 | J74: 1484 | L74: 589 | M74: /storage/images/Apple MacBook Pro 13 inch Touch Bar M1.png | N74: 228 | O74: 230 | P74: 231 | Q74: #E4E6E7 | R74: x
A75: MBAM1 | B75: Apple MacBook Air M1 | C75: 1 | D75: Laptop | E75: =IF(D75 = "","", INDEX(Categories!$A$2:$A$5, MATCH(D75,Categories!$B$2:$B$5, 0))) -> 3 | F75: Apple | G75: =IF(F75 = "","",INDEX(Brands!$A$2:$A$5, MATCH(F75,Brands!$B$2:$B$5))) -> 1 | H75: 680 | J75: 948 | L75: 981 | M75: /storage/images/Apple MacBook Air M1.png | N75: 172 | O75: 129 | P75: 104 | Q75: #AC8168 | R75: x
E76: =IF(D76 = "","", INDEX(Categories!$A$2:$A$5, MATCH(D76,Categories!$B$2:$B$5, 0))) | G76: =IF(F76 = "","",INDEX(Brands!$A$2:$A$5, MATCH(F76,Brands!$B$2:$B$5)))
A77: LGG202317ZGAH78 | B77: Laptop LG Gram 2023 17Z90R-G.AH78A5 | C77: 1 | D77: Laptop | E77: =IF(D77 = "","", INDEX(Categories!$A$2:$A$5, MATCH(D77,Categories!$B$2:$B$5, 0))) -> 3 | F77: LG | G77: =IF(F77 = "","",INDEX(Brands!$A$2:$A$5, MATCH(F77,Brands!$B$2:$B$5))) -> 1 | H77: 1643 | J77: 2094 | L77: 760 | M77: /storage/images/Laptop LG Gram 2023 17Z90R-G.AH78A5.png | N77: 72 | O77: 72 | P77: 72 | Q77: #484848 | R77: x
A78: LGG202317ZGAX73 | B78: Laptop LG Gram 2023 17ZD90R-G.AX73A5 | C78: 1 | D78: Laptop | E78: =IF(D78 = "","", INDEX(Categories!$A$2:$A$5, MATCH(D78,Categories!$B$2:$B$5, 0))) -> 3 | F78: LG | G78: =IF(F78 = "","",INDEX(Brands!$A$2:$A$5, MATCH(F78,Brands!$B$2:$B$5))) -> 1 | H78: 1355 | J78: 1766 | L78: 831 | M78: /storage/images/Laptop LG Gram 2023 17ZD90R-G.AX73A5.png | N78: 87 | O78: 87 | P78: 91 | Q78: #57575B | R78: x
A79: LGG202316ZGAH76 | B79: Laptop LG Gram 2023 16Z90R-G.AH76A5 | C79: 1 | D79: Laptop | E79: =IF(D79 = "","", INDEX(Categories!$A$2:$A$5, MATCH(D79,Categories!$B$2:$B$5, 0))) -> 3 | F79: LG | G79: =IF(F79 = "","",INDEX(Brands!$A$2:$A$5, MATCH(F79,Brands!$B$2:$B$5))) -> 1 | H79: 1560 | J79: 1930 | L79: 458 | M79: /storage/images/Laptop LG Gram 2023 16Z90R-G.AH76A5.png | N79: 82 | O79: 81 | P79: 86 | Q79: #525156 | R79: x
A80: LGG202316ZEAH75 | B80: Laptop LG Gram 2023 16Z90R-E.AH75A5 | C80: 1 | D80: Laptop | E80: =IF(D80 = "","", INDEX(Categories!$A$2:$A$5, MATCH(D80,Categories!$B$2:$B$5, 0))) -> 3 | F80: LG | G80: =IF(F80 = "","",INDEX(Brands!$A$2:$A$5, MATCH(F80,Brands!$B$2:$B$5))) -> 1 | H80: 1601 | J80: 2053 | L80: 939 | M80: /storage/images/Laptop LG Gram 2023 16Z90R-E.AH75A5.png | N80: 69 | O80: 69 | P80: 69 | Q80: #454545 | R80: x
A81: LGG202316ZGAH54 | B81: Laptop LG Gram 2023 16Z90RS-G.AH54A5 | C81: 1 | D81: Laptop | E81: =IF(D81 = "","", INDEX(Categories!$A$2:$A$5, MATCH(D81,Categories!$B$2:$B$5, 0))) -> 3 | F81: LG | G81: =IF(F81 = "","",INDEX(Brands!$A$2:$A$5, MATCH(F81,Brands!$B$2:$B$5))) -> 1 | H81: 1437 | J81: 1807 | L81: 274 | M81: /storage/images/Laptop LG Gram 2023 16Z90RS-G.AH54A5.png | N81: 198 | O81: 196 | P81: 208 | Q81: #C6C4D0 | R81: x
A82: LGG202315ZGAH55 | B82: Laptop LG Gram 2023 15Z90RT-G.AH55A5 | C82: 1 | D82: Laptop | E82: =IF(D82 = "","", INDEX(Categories!$A$2:$A$5, MATCH(D82,Categories!$B$2:$B$5, 0))) -> 3 | F82: LG | G82: =IF(F82 = "","",INDEX(Brands!$A$2:$A$5, MATCH(F82,Brands!$B$2:$B$5))) -> 1 | H82: 1396 | J82: 1766 | L82: 47 | M82: /storage/images/Laptop LG Gram 2023 15Z90RT-G.AH55A5.png | N82: 61 | O82: 60 | P82: 65 | Q82: #3D3C41 | R82: x
A83: LGG202314ZGAH75 | B83: Laptop LG Gram 2023 14Z90R-G.AH75A5 | C83: 1 | D83: Laptop | E83: =IF(D83 = "","", INDEX(Categories!$A$2:$A$5, MATCH(D83,Categories!$B$2:$B$5, 0))) -> 3 | F83: LG | G83: =IF(F83 = "","",INDEX(Brands!$A$2:$A$5, MATCH(F83,Brands!$B$2:$B$5))) -> 1 | H83: 1253 | J83: 1601 | L83: 358 | M83: /storage/images/Laptop LG Gram 2023 14Z90R-G.AH75A5.png | N83: 74 | O83: 74 | P83: 74 | Q83: #4A4A4A | R83: x
A84: LGG202314ZGAH54 | B84: Laptop LG Gram 2023 14Z90RS-G.AH54A5 | C84: 1 | D84: Laptop | E84: =IF(D84 = "","", INDEX(Categories!$A$2:$A$5, MATCH(D84,Categories!$B$2:$B$5, 0))) -> 3 | F84: LG | G84: =IF(F84 = "","",INDEX(Brands!$A$2:$A$5, MATCH(F84,Brands!$B$2:$B$5))) -> 1 | H84: 1232 | J84: 1601 | L84: 917 | M84: /storage/images/Laptop LG Gram 2023 14Z90RS-G.AH54A5.png | N84: 194 | O84: 192 | P84: 205 | Q84: #C2C0CD | R84: x
A85: LGG202314ZGAH53 | B85: Laptop LG Gram 2023 14Z90R-G.AH53A5 | C85: 1 | D85: Laptop | E85: =IF(D85 = "","", INDEX(Categories!$A$2:$A$5, MATCH(D85,Categories!$B$2:$B$5, 0))) -> 3 | F85: LG | G85: =IF(F85 = "","",INDEX(Brands!$A$2:$A$5, MATCH(F85,Brands!$B$2:$B$5))) -> 1 | H85: 986 | J85: 1335 | L85: 16 | M85: /storage/images/Laptop LG Gram 2023 14Z90R-G.AH53A5.png | N85: 106 | O85: 106 | P85: 106 | Q85: #6A6A6A | R85: x
A86: LGG202314ZGAX51 | B86: Laptop LG Gram 2023 14ZD90R-G.AX51A5 | C86: 1 | D86: Laptop | E86: =IF(D86 = "","", INDEX(Categories!$A$2:$A$5, MATCH(D86,Categories!$B$2:$B$5, 0))) -> 3 | F86: LG | G86: =IF(F86 = "","",INDEX(Brands!$A$2:$A$5, MATCH(F86,Brands!$B$2:$B$5))) -> 1 | H86: 863 | J86: 1191 | L86: 687 | M86: /storage/images/Laptop LG Gram 2023 14ZD90R-G.AX51A5.png | N86: 236 | O86: 236 | P86: 236 | Q86: #ECECEC | R86: x
A87: LGG202314ZGAX52 | B87: Laptop LG Gram 2023 14ZD90R-G.AX52A5 | C87: 1 | D87: Laptop | E87: =IF(D87 = "","", INDEX(Categories!$A$2:$A$5, MATCH(D87,Categories!$B$2:$B$5, 0))) -> 3 | F87: LG | G87: =IF(F87 = "","",INDEX(Brands!$A$2:$A$5, MATCH(F87,Brands!$B$2:$B$5))) -> 1 | H87: 780 | J87: 1068 | L87: 571 | M87: /storage/images/Laptop LG Gram 2023 14ZD90R-G.AX52A5.png | N87: 68 | O87: 68 | P87: 68 | Q87: #444444 | R87: x
A88: LGG202114ZGAH75 | B88: Laptop LG Gram 2021 14Z90P-G.AH75A5 14 inch | C88: 1 | D88: Laptop | E88: =IF(D88 = "","", INDEX(Categories!$A$2:$A$5, MATCH(D88,Categories!$B$2:$B$5, 0))) -> 3 | F88: LG | G88: =IF(F88 = "","",INDEX(Brands!$A$2:$A$5, MATCH(F88,Brands!$B$2:$B$5))) -> 1 | H88: 1027 | J88: 1696 | L88: 620 | M88: /storage/images/Laptop LG Gram 2021 14Z90P-G.AH75A5 14 inch.png | N88: 64 | O88: 64 | P88: 64 | Q88: #404040 | R88: x
A89: LGG2I114T | B89: Laptop LG Gram 2IN1 14T90R-G.AH55A5 | C89: 1 | D89: Laptop | E89: =IF(D89 = "","", INDEX(Categories!$A$2:$A$5, MATCH(D89,Categories!$B$2:$B$5, 0))) -> 3 | F89: LG | G89: =IF(F89 = "","",INDEX(Brands!$A$2:$A$5, MATCH(F89,Brands!$B$2:$B$5))) -> 1 | H89: 1191 | J89: 1766 | L89: 177 | M89: /storage/images/Laptop LG Gram 2IN1 14T90R-G.AH55A5.png | N89: 64 | O89: 64 | P89: 64 | Q89: #404040 | R89: x
A90: Watch
A91: SW6C47B | B91: Samsung Galaxy Watch 6 Classic 47mm Bluetooth | C91: 1 | D91: Watch | E91: =IF(D91 = "","", INDEX(Categories!$A$2:$A$5, MATCH(D91,Categories!$B$2:$B$5, 0))) -> 1 | F91: SamSung | G91: =IF(F91 = "","",INDEX(Brands!$A$2:$A$5, MATCH(F91,Brands!$B$2:$B$5))) -> 2 | H91: 289 | J91: 392 | L91: 471 | M91: /storage/images/Samsung Galaxy Watch 6 Classic 47mm Bluetooth.png | N91: 59 | O91: 59 | P91: 59 | Q91: #3B3B3B | R91: x
A92: SW6 | B92: Samsung Galaxy Watch 6 44mm | C92: 1 | D92: Watch | E92: =IF(D92 = "","", INDEX(Categories!$A$2:$A$5, MATCH(D92,Categories!$B$2:$B$5, 0))) -> 1 | F92: SamSung | G92: =IF(F92 = "","",INDEX(Brands!$A$2:$A$5, MATCH(F92,Brands!$B$2:$B$5))) -> 2 | H92: 165 | J92: 310 | L92: 389 | M92: /storage/images/Samsung Galaxy Watch 6 44mm.png | N92: 204 | O92: 208 | P92: 211 | Q92: #CCD0D3 | R92: x
A93: SW6C43B | B93: Samsung Galaxy Watch 6 Classic 43mm Bluetooth | C93: 1 | D93: Watch | E93: =IF(D93 = "","", INDEX(Categories!$A$2:$A$5, MATCH(D93,Categories!$B$2:$B$5, 0))) -> 1 | F93: SamSung | G93: =IF(F93 = "","",INDEX(Brands!$A$2:$A$5, MATCH(F93,Brands!$B$2:$B$5))) -> 2 | H93: 268 | J93: 371 | L93: 427 | M93: /storage/images/Samsung Galaxy Watch 6 Classic 43mm Bluetooth.png | N93: 187 | O93: 191 | P93: 194 | Q93: #BBBFC2 | R93: x
A94: SW640 | B94: Samsung Galaxy Watch 6 40mm | C94: 1 | D94: Watch | E94: =IF(D94 = "","", INDEX(Categories!$A$2:$A$5, MATCH(D94,Categories!$B$2:$B$5, 0))) -> 1 | F94: SamSung | G94: =IF(F94 = "","",INDEX(Brands!$A$2:$A$5, MATCH(F94,Brands!$B$2:$B$5))) -> 2 | H94: 205 | J94: 289 | L94: 335 | M94: /storage/images/Samsung Galaxy Watch 6 40mm.png | N94: 67 | O94: 69 | P94: 81 | Q94: #434551 | R94: x
A95: SW5P | B95: Samsung Galaxy Watch 5 Pro | C95: 1 | D95: Watch | E95: =IF(D95 = "","", INDEX(Categories!$A$2:$A$5, MATCH(D95,Categories!$B$2:$B$5, 0))) -> 1 | F95: SamSung | G95: =IF(F95 = "","",INDEX(Brands!$A$2:$A$5, MATCH(F95,Brands!$B$2:$B$5))) -> 2 | H95: 310 | J95: 495 | L95: 505 | M95: /storage/images/Samsung Galaxy Watch 5 Pro.png | N95: 38 | O95: 38 | P95: 38 | Q95: #262626 | R95: x
A96: SW544 | B96: Samsung Galaxy Watch 5 44mm | C96: 1 | D96: Watch | E96: =IF(D96 = "","", INDEX(Categories!$A$2:$A$5, MATCH(D96,Categories!$B$2:$B$5, 0))) -> 1 | F96: SamSung | G96: =IF(F96 = "","",INDEX(Brands!$A$2:$A$5, MATCH(F96,Brands!$B$2:$B$5))) -> 2 | H96: 227 | J96: 268 | L96: 573 | M96: /storage/images/Samsung Galaxy Watch 5 44mm.png | N96: 122 | O96: 135 | P96: 151 | Q96: #7A8797 | R96: x
A97: SW544LTE | B97: Samsung Galaxy Watch 5 44mm LTE | C97: 1 | D97: Watch | E97: =IF(D97 = "","", INDEX(Categories!$A$2:$A$5, MATCH(D97,Categories!$B$2:$B$5, 0))) -> 1 | F97: SamSung | G97: =IF(F97 = "","",INDEX(Brands!$A$2:$A$5, MATCH(F97,Brands!$B$2:$B$5))) -> 2 | H97: 289 | J97: 330 | L97: 735 | M97: /storage/images/Samsung Galaxy Watch 5 44mm LTE.png | N97: 95 | O97: 96 | P97: 100 | Q97: #5F6064 | R97: x
E98: =IF(D98 = "","", INDEX(Categories!$A$2:$A$5, MATCH(D98,Categories!$B$2:$B$5, 0))) | G98: =IF(F98 = "","",INDEX(Brands!$A$2:$A$5, MATCH(F98,Brands!$B$2:$B$5)))
A99: AWS945 | B99: Apple Watch Series 9 45mm | C99: 1 | D99: Watch | E99: =IF(D99 = "","", INDEX(Categories!$A$2:$A$5, MATCH(D99,Categories!$B$2:$B$5, 0))) -> 1 | F99: Apple | G99: =IF(F99 = "","",INDEX(Brands!$A$2:$A$5, MATCH(F99,Brands!$B$2:$B$5))) -> 1 | H99: 413 | J99: 503 | L99: 621 | M99: /storage/images/Apple Watch Series 9 45mm.png | N99: 211 | O99: 201 | P99: 192 | Q99: #D3C9C0 | R99: x
A100: AWS941 | B100: Apple Watch Series 9 41mm | C100: 1 | D100: Watch | E100: =IF(D100 = "","", INDEX(Categories!$A$2:$A$5, MATCH(D100,Categories!$B$2:$B$5, 0))) -> 1 | F100: Apple | G100: =IF(F100 = "","",INDEX(Brands!$A$2:$A$5, MATCH(F100,Brands!$B$2:$B$5))) -> 1 | H100: 371 | J100: 433 | L100: 154 | M100: /storage/images/Apple Watch Series 9 41mm.png | N100: 55 | O100: 56 | P100: 64 | Q100: #373840 | R100: x
A101: AWS845 | B101: Apple Watch Series 8 45mm | C101: 1 | D101: Watch | E101: =IF(D101 = "","", INDEX(Categories!$A$2:$A$5, MATCH(D101,Categories!$B$2:$B$5, 0))) -> 1 | F101: Apple | G101: =IF(F101 = "","",INDEX(Brands!$A$2:$A$5, MATCH(F101,Brands!$B$2:$B$5))) -> 1 | H101: 330 | J101: 536 | L101: 908 | M101: /storage/images/Apple Watch Series 8 45mm.png | N101: 233 | O101: 232 | P101: 230 | Q101: #E9E8E6 | R101: x
A102: AWS841 | B102: Apple Watch Series 8 41mm | C102: 1 | D102: Watch | E102: =IF(D102 = "","", INDEX(Categories!$A$2:$A$5, MATCH(D102,Categories!$B$2:$B$5, 0))) -> 1 | F102: Apple | G102: =IF(F102 = "","",INDEX(Brands!$A$2:$A$5, MATCH(F102,Brands!$B$2:$B$5))) -> 1 | H102: 330 | J102: 495 | L102: 962 | M102: /storage/images/Apple Watch Series 8 41mm.png | N102: 214 | O102: 48 | P102: 72 | Q102: #D63048 | R102: x
A103: AWS745 | B103: Apple Watch Series 7 45mm | C103: 1 | D103: Watch | E103: =IF(D103 = "","", INDEX(Categories!$A$2:$A$5, MATCH(D103,Categories!$B$2:$B$5, 0))) -> 1 | F103: Apple | G103: =IF(F103 = "","",INDEX(Brands!$A$2:$A$5, MATCH(F103,Brands!$B$2:$B$5))) -> 1 | H103: 310 | J103: 536 | L103: 680 | M103: /storage/images/Apple Watch Series 7 45mm.png | N103: 54 | O103: 55 | P103: 62 | Q103: #36373E | R103: x
...

Sheet Sale
A1: Name Tên khuyến mãi | B1: Name Mã khuyến mãi | C1: Price Giá tiền giảm | D1: Rank Hạng thành viên được áp dụng | E1: Amount Số lượng | F1: Date Start Ngày bắt đầu | G1: Date End Ngày kết thúc
A2: Sale 10 | B2: SALE10 | C2: 10 | D2: Đồng | E2: 100 | F2: 2023-12-31 | G2: 2050-12-31
A3: Sale 10000000 | B3: SALEOVERPRICE | C3: 10000000 | D3: Đồng | E3: 200 | F3: 2023-12-31 | G3: 2050-12-31
A4: Sale Expired | B4: SALEEXPIRED | C4: 100 | D4: Đồng | E4: 200 | F4: 2023-11-01 | G4: 2023-12-01
A5: Out Of Sale | B5: OUTOFSALE | C5: 100 | D5: Đồng | E5: 0 | F5: 2023-11-01 | G5: 2050-12-31

Sheet Rank
A1: Name Tên hạng thành viên | B1: Discount % Tỷ lệ giảm giá | C1: Value Số tiền cần đạt ? | D1: Description Mô tả
A2: Đồng | B2: 5 | C2: 10000 | D2: Cho người mới vào

Sheet Bank Account
A1: Ngân hàng | B1: Số thẻ | C1: Tên chủ thẻ | D1: Ngày phát hành | E1: OTP | F1: Ghi chú | G1: Thông báo trên hệ thống
A2: NCB | B2: 9704198526191432198 | C2: NGUYEN VAN A | D2: 07/15 | E2: 123456 | F2: Thành công
A3: NCB | B3: 9704195798459170488 | C3: NGUYEN VAN A | D3: 07/15 | F3: Thẻ không đủ số dư | G3: Your account does not have enough balance for the transaction
A4: NCB | B4: 9704192181368742 | C4: NGUYEN VAN A | D4: 07/15 | F4: Thẻ chưa kích hoạt | G4: Your card hasn’t been active
A5: NCB | B5: 9704193370791314 | C5: NGUYEN VAN A | D5: 07/15 | F5: Thẻ bị khóa | G5: Card locked
A6: NCB | B6: 9704194841945513 | C6: NGUYEN VAN A | D6: 07/15 | F6: Thẻ bị hết hạn | G6: Card expires
